sudalTest/test1.py
sudalTest/test2.py
sudalTest-0.0.0.2.dist-info/METADATA
sudalTest-0.0.0.2.dist-info/WHEEL
sudalTest-0.0.0.2.dist-info/top_level.txt
sudalTest-0.0.0.2.dist-info/RECORD
