Metadata-Version: 2.1
Name: sudalTest
Version: 0.0.0.2
Summary: My First Test Package
Home-page: https://blog.naver.com/feat4001
Author: Seung Rok
Author-email: feat4001@naver.com
License: MIT
Platform: UNKNOWN
Requires-Python: >=3
